wombopy/__init__.py
wombopy/__main__.py
wombopy/cli.py
wombopy/config.py
wombopy/logging.py
wombopy/core/__init__.py
wombopy/core/generation.py
wombopy/core/identify.py
wombopy-0.2.2.dist-info/METADATA
wombopy-0.2.2.dist-info/WHEEL
wombopy-0.2.2.dist-info/top_level.txt
wombopy-0.2.2.dist-info/RECORD
