Metadata-Version: 2.1
Name: wombopy
Version: 0.2.2
Summary: A module to generate wombo.art images
Author: Holy Tanuki
Requires-Python: >=3.7.13
Requires-Dist: typer (==0.7.0)
Requires-Dist: colorama (==0.4.6)
Requires-Dist: shellingham (==1.5.0post1)
Requires-Dist: pytest (==7.1.2)
Requires-Dist: requests (==2.28.2)
